deepcore/__init__.py
deepcore/main.py
deepcore-1.2.2.dist-info/licenses/LICENSE
deepcore-1.2.2.dist-info/METADATA
deepcore-1.2.2.dist-info/WHEEL
deepcore-1.2.2.dist-info/top_level.txt
deepcore-1.2.2.dist-info/RECORD
