Metadata-Version: 2.4
Name: deepcore
Version: 1.2.2
Author: vishal singh
Author-email: vishalsinghomr@gmail.com
Keywords: measurement of central tendency,library,python,mean,,median,mode,multimode
Classifier: Programming Language :: Python :: 3
Classifier: License :: OSI Approved :: MIT License
Classifier: Operating System :: MacOS :: MacOS X
Classifier: Operating System :: Microsoft :: Windows
Requires-Python: >=3.6
License-File: LICENSE
Dynamic: author
Dynamic: author-email
Dynamic: classifier
Dynamic: description
Dynamic: description-content-type
Dynamic: keywords
Dynamic: license-file
Dynamic: requires-python
